eve/__init__.py
eve/version.py
eve/app/__init__.py
eve/app/mnist.py
eve/app/trainer.py
eve/app/vggm.py
eve/cores/__init__.py
eve/cores/encoder.py
eve/cores/eve.py
eve/cores/layers.py
eve/cores/node.py
eve/cores/quan.py
eve/cores/utils.py
eve/rl/__init__.py
eve/rl/exp_manager.py
eve/rl/agent/__init__.py
eve/rl/agent/policies.py
eve/rl/envs/__init__.py
eve/rl/envs/nas.py
eve/rl/utils/__init__.py
eve/rl/utils/callbacks.py
eve/rl/utils/hyperparams_opt.py
eve/rl/utils/import_envs.py
eve/rl/utils/utils.py
eve/upgrade/__init__.py
eve/upgrade/upgrader.py
eve/utils/__init__.py
eve/utils/legacy.py
Eve_ml-0.0.1.dist-info/LICENSE
Eve_ml-0.0.1.dist-info/METADATA
Eve_ml-0.0.1.dist-info/WHEEL
Eve_ml-0.0.1.dist-info/top_level.txt
Eve_ml-0.0.1.dist-info/RECORD
