Metadata-Version: 2.1
Name: Eve-ml
Version: 0.0.1
Summary: Eve: make deep learning more interesting.
Home-page: https://github.com/densechen/eve
Author: densechen
Author-email: densechen@foxmail.com
License: MIT
Platform: UNKNOWN
Classifier: Programming Language :: Python :: 3 :: Only
Classifier: Programming Language :: Python :: 3.6
Classifier: Programming Language :: Python :: 3.7
Classifier: Programming Language :: Python :: 3.8
Classifier: Operating System :: OS Independent
Requires-Python: >=3.6
Requires-Dist: gym (==0.18.0)
Requires-Dist: numpy (==1.18.5)
Requires-Dist: optuna (==2.3.0)
Requires-Dist: seaborn (==0.11.0)
Requires-Dist: stable-baselines3 (==0.10.0)
Requires-Dist: tensorboard (==2.4.0)
Requires-Dist: tensorboard-plugin-wit (==1.7.0)
Requires-Dist: torch (==1.7.0)
Requires-Dist: torchfile (==0.1.0)
Requires-Dist: torchnet (==0.0.4)
Requires-Dist: torchvision (==0.8.1)
